segcheck/__init__.py
segcheck/core.py
segcheck/exceptions.py
tests/__init__.py
segcheck-0.0.1.dist-info/METADATA
segcheck-0.0.1.dist-info/WHEEL
segcheck-0.0.1.dist-info/top_level.txt
segcheck-0.0.1.dist-info/RECORD
