Metadata-Version: 2.1
Name: segcheck
Version: 0.0.1
Summary: segcheck helps to find gaps and overlaps in linear segments
Home-page: https://github.com/thomasschus/segcheck
Author: thomasschus
Author-email: thomas.schus@gmail.com
License: UNKNOWN
Platform: UNKNOWN
Classifier: Programming Language :: Python :: 3
Classifier: Operating System :: OS Independent
Requires-Python: >=3.6
